codewright/__init__.py
codewright/cli.py
codewright/decorators.py
codewright-0.1.0.dist-info/METADATA
codewright-0.1.0.dist-info/WHEEL
codewright-0.1.0.dist-info/entry_points.txt
codewright-0.1.0.dist-info/top_level.txt
codewright-0.1.0.dist-info/RECORD
