Metadata-Version: 2.4
Name: codewright
Version: 0.1.0
Summary: A CLI and utility package with decorators and tools to accelerate development.
Author-email: Srajan <srajansolanki04@gmail.com>
Classifier: Programming Language :: Python :: 3
Classifier: License :: OSI Approved :: MIT License
Classifier: Operating System :: OS Independent
Classifier: Intended Audience :: Developers
Requires-Python: >=3.8
Requires-Dist: click>=8.0
